pandas_geojson/__init__.py
pandas_geojson/core.py
pandas_geojson/io.py
pandas_geojson-2.2.1.dist-info/LICENSE
pandas_geojson-2.2.1.dist-info/METADATA
pandas_geojson-2.2.1.dist-info/WHEEL
pandas_geojson-2.2.1.dist-info/top_level.txt
pandas_geojson-2.2.1.dist-info/RECORD
