Metadata-Version: 2.1
Name: pandas_geojson
Version: 2.2.1
Summary: Manage GeoJSON Files
Home-page: https://github.com/jrasband-dev/pandas-geojson
Author: Jayden Rasband
Author-email: jayden.rasband@gmail.com
License: MIT
Classifier: Programming Language :: Python :: 3
Classifier: Programming Language :: Python :: 3.9
License-File: LICENSE
